<Properties StartupConfiguration="{52095CA7-8B9F-4CF5-932C-7E14D308FE7A}|Default">
  <MonoDevelop.Ide.ItemProperties.vr180ToEquiPhoto PreferredExecutionTarget="MonoDevelop.Default" />
  <MonoDevelop.Ide.Workbench ActiveDocument="atomlib/Container.cs">
    <Files>
      <File FileName="convertToVr180Photo/Program.cs" Line="23" Column="1" />
      <File FileName="convertVr180Photos/Program.cs" Line="31" Column="10" />
      <File FileName="atomlib/Container.cs" Line="14" Column="21" />
    </Files>
  </MonoDevelop.Ide.Workbench>
  <MonoDevelop.Ide.ItemProperties.rmrotation PreferredExecutionTarget="MonoDevelop.Default" />
  <MonoDevelop.Ide.DebuggingService.PinnedWatches />
  <MonoDevelop.Ide.ItemProperties.equiToVr180Photo PreferredExecutionTarget="MonoDevelop.Default" />
  <MonoDevelop.Ide.Workspace ActiveConfiguration="Debug|x86" />
  <MonoDevelop.Ide.DebuggingService.Breakpoints>
    <BreakpointStore>
      <Breakpoint file="/Users/davidburnett/Projects/VR180Tools/atomlib/Atom.cs" relfile="atomlib/Atom.cs" line="16" column="1" />
      <Breakpoint file="/Users/davidburnett/Projects/VR180Tools/VR180Tools/Program.cs" relfile="VR180Tools/Program.cs" line="82" column="1" />
      <Breakpoint file="/Users/davidburnett/Projects/VR180Tools/VR180Tools/Program.cs" relfile="VR180Tools/Program.cs" line="87" column="1" />
      <Breakpoint file="/Users/davidburnett/Projects/VR180Tools/VR180Tools/Program.cs" relfile="VR180Tools/Program.cs" line="74" column="1" />
    </BreakpointStore>
  </MonoDevelop.Ide.DebuggingService.Breakpoints>
  <MultiItemStartupConfigurations />
</Properties>